<?xml version="1.0" encoding="UTF-8"?>
<?xml-model href="dplava.xsd" type="application/xml" schematypens="http://purl.oclc.org/dsdl/schematron"?>
<mdRecord xmlns="http://dplava.lib.virginia.edu" xmlns:xsi="http://www.w3.org/2001/XMLSchema-instance" xmlns:dc="http://purl.org/dc/elements/1.1/" xmlns:dcterms="http://purl.org/dc/terms/" xmlns:rdf="http://www.w3.org/1999/02/22-rdf-syntax-ns#" xmlns:edm="http://www.europeana.eu/schemas/edm/" xsi:schemaLocation="http://dplava.lib.virginia.edu/dplava.xsd">
<dcterms:rights>http://rightsstatements.org/vocab/NoC-US/1.0/</dcterms:rights>
<dcterms:provenance>Washington and Lee University</dcterms:provenance>
<dcterms:isPartOf>Walker-Wood Family Papers, 1910-1975</dcterms:isPartOf>
<dcterms:identifier>WLUColl0294_b04_f086</dcterms:identifier>
<edm:isShownAt>https://dspace.wlu.edu/handle/11021/35645</edm:isShownAt>
<dcterms:description>This is Nannie Walker's notebook on the Bible while at Hartshorn [Memorial] College in Richmond, Virginia.  The date written on the inside cover is October 1, 1914.</dcterms:description>
<dcterms:language>en_US</dcterms:language>
<dcterms:title>Nannie Walker's Notebook on the Bible, October 1, 1914</dcterms:title>
<dcterms:type>Text</dcterms:type>
<dcterms:subject>Bible study</dcterms:subject>
<dcterms:subject>Hartshorn Memorial College (Richmond, Va.)</dcterms:subject>
<edm:preview>https://dspace.wlu.edu/rest/bitstreams/a3151c8b-74e2-49b2-b179-fb3c0411a6fe/retrieve</edm:preview>
</mdRecord>
